setup.cfg
setup.py
pylsa/lsa.py
pylsa/run_me.py
pylsa/tests.py
pylsa.egg-info/PKG-INFO
pylsa.egg-info/SOURCES.txt
pylsa.egg-info/dependency_links.txt
pylsa.egg-info/requires.txt
pylsa.egg-info/top_level.txt