Metadata-Version: 1.0
Name: pylsa
Version: 0.1
Summary: lsa
Home-page: https://github.com/llazzaro/lsa_python
Author: Leonardo Lazzaro
Author-email: lazzaroleonardo@gmail.com
License: UNKNOWN
Platform: UNKNOWN
